smart_tsp_solver/__init__.py
smart_tsp_solver/algorithms/__init__.py
smart_tsp_solver/algorithms/angular_radial/__init__.py
smart_tsp_solver/algorithms/angular_radial/v1.py
smart_tsp_solver/algorithms/angular_radial/v2.py
smart_tsp_solver/algorithms/dynamic_gravity/__init__.py
smart_tsp_solver/algorithms/dynamic_gravity/v1.py
smart_tsp_solver/algorithms/dynamic_gravity/v2.py
smart_tsp_solver/algorithms/hierarchical/__init__.py
smart_tsp_solver/algorithms/hierarchical/v1.py
smart_tsp_solver/algorithms/hierarchical/v2.py
smart_tsp_solver/algorithms/other/__init__.py
smart_tsp_solver/algorithms/other/greedy/__init__.py
smart_tsp_solver/algorithms/other/greedy/v1.py
smart_tsp_solver/algorithms/other/greedy/v2.py
smart_tsp_solver-1.0.0.dist-info/licenses/LICENSE
smart_tsp_solver-1.0.0.dist-info/METADATA
smart_tsp_solver-1.0.0.dist-info/WHEEL
smart_tsp_solver-1.0.0.dist-info/top_level.txt
smart_tsp_solver-1.0.0.dist-info/RECORD
