Metadata-Version: 2.4
Name: smart-tsp-solver
Version: 1.0.0
Summary: A high-performance Python library for solving the Traveling Salesman Problem (TSP) using novel heuristic approaches. Features advanced algorithms that outperform classical methods by ~25% on real-world clustered data while maintaining practical computational efficiency.
Author-email: "A.A Suvorov" <smartlegiondev@gmail.com>
License-Expression: BSD-3-Clause
Project-URL: Homepage, https://github.com/smartlegionlab/smart-tsp-solver
Classifier: Programming Language :: Python :: 3
Classifier: Operating System :: OS Independent
Requires-Python: >=3.6
License-File: LICENSE
Requires-Dist: smart-tsp-benchmark~=1.0.0
Requires-Dist: numba==0.61.2
Dynamic: license-file
